wfmeta_darshan/__init__.py
wfmeta_darshan/__main__.py
wfmeta_darshan/objs/__init__.py
wfmeta_darshan/objs/colls.py
wfmeta_darshan/objs/log.py
wfmeta_darshan-1.0.0.dist-info/licenses/LICENSE
wfmeta_darshan-1.0.0.dist-info/METADATA
wfmeta_darshan-1.0.0.dist-info/WHEEL
wfmeta_darshan-1.0.0.dist-info/entry_points.txt
wfmeta_darshan-1.0.0.dist-info/top_level.txt
wfmeta_darshan-1.0.0.dist-info/RECORD
