Metadata-Version: 2.4
Name: wfmeta_darshan
Version: 1.0.0
Summary: The WFMeta tool to read and aggregate Darshan logs.
Author-email: Polina Shpilker <infinite.loopholes@gmail.com>
License-Expression: MIT
Project-URL: Homepage, https://github.com/infispiel/wfmeta-darshan
Requires-Python: >=3.10
License-File: LICENSE
Requires-Dist: pyarrow>=17.0.0
Requires-Dist: pandas
Dynamic: license-file
